thread_signals/__init__.py
thread_signals/late_start_thread.py
thread_signals/patcher.py
thread_signals/task.py
thread_signals/task_broker.py
thread_signals-1.0.0.dist-info/METADATA
thread_signals-1.0.0.dist-info/WHEEL
thread_signals-1.0.0.dist-info/top_level.txt
thread_signals-1.0.0.dist-info/RECORD
